{"symptoms":[{"adaptation-property":"EstadoAsiento","value":true}],"rules-proposal":"{\"components\":[{\"id\":\"interaction.NotificationService\",\"version\":\"1.0.0\"},{\"id\":\"interaction.Seat.Driver\",\"version\":\"1.0.0\"},{\"id\":\"interaction.DriverDisplay.VisualIcon\",\"version\":\"1.0.0\"}],\"reference-model\":\"AutonomousCar\",\"bindings\":[{\"requiring\":{\"component\":{\"id\":\"interaction.NotificationService\",\"version\":\"1.0.0\"},\"interface\":\"required_mechanisms\"},\"supplying\":{\"component\":{\"id\":\"interaction.Seat.Driver\",\"version\":\"1.0.0\"},\"interface\":\"provided_mechanism\"}},{\"requiring\":{\"component\":{\"id\":\"interaction.NotificationService\",\"version\":\"1.0.0\"},\"interface\":\"required_mechanisms\"},\"supplying\":{\"component\":{\"id\":\"interaction.DriverDisplay.VisualIcon\",\"version\":\"1.0.0\"},\"interface\":\"provided_mechanism\"}}],\"id\":\"Regla Interaccion Asiento_202505031644170785\",\"timestamp\":\"202505031644170830\"}","adaptation-plan-actions-exceptions":[],"correlation-id":"a8de99ed16d145c992c431e4fad04e21","current-system-configurarion":"{\"components\":[{\"id\":\"device.RoadSensor\",\"version\":\"1.0.0\"}],\"reference-model\":\"AutonomousCar\",\"id\":\"InititalConfiguration\",\"timestamp\":\"202505031644170829\"}","next-system-configurarion":"-- PLAN (a8de99ed16d145c992c431e4fad04e21) --\nDEPLOY interaction.NotificationService_1.0.0\nDEPLOY interaction.Seat.Driver_1.0.0\nDEPLOY interaction.DriverDisplay.VisualIcon_1.0.0\nBIND interaction.NotificationService_1.0.0::required_mechanisms -C   o- interaction.Seat.Driver_1.0.0::provided_mechanism\nBIND interaction.NotificationService_1.0.0::required_mechanisms -C   o- interaction.DriverDisplay.VisualIcon_1.0.0::provided_mechanism\n-- END PLAN --","id":"report-a8de99ed16d145c992c431e4fad04e21","initiated-by-rule":"Regla Interaccion Asiento","timestamp":"202505031644170829","status":[{"status":"REQUESTED","timestamp":"202505031644170778"},{"status":"IN_PROGRESS","timestamp":"202505031644170794"},{"status":"SUCCEEDED","timestamp":"202505031644170829"}]}